[
  {
    "user_id": "bacasd",
    "name": "Abhinav Singh",
    "hashedPassword": "12345",
    "tickets_booked": [
      {
        "source": "Bangalore",
        "destination": "Mumbai",
        "date_of_travel": "2025-09-23T12:30:00Z",
        "train": {
          "train_id": "asdf",
          "train_no": 124656,
          "seats": [
            [0,0,0,0,0,0],
            [0,0,0,0,0,0],
            [0,0,0,0,0,0],
            [0,0,0,0,0,0]
          ],
          "stations": {
            "Bangalore": "13:40:00",
            "jaipur": "14:30:00",
            "Delhi": "15:30:00"
          }
        }
      }
    ]
  }
]